swmmtoolbox/__init__.py
swmmtoolbox/swmmtoolbox.py
swmmtoolbox/toolbox_utils/docs/conf.py
swmmtoolbox/toolbox_utils/src/toolbox_utils/__init__.py
swmmtoolbox/toolbox_utils/src/toolbox_utils/tsutils.py
swmmtoolbox/toolbox_utils/src/toolbox_utils/readers/__init__.py
swmmtoolbox/toolbox_utils/src/toolbox_utils/readers/hbn.py
swmmtoolbox/toolbox_utils/src/toolbox_utils/readers/plotgen.py
swmmtoolbox/toolbox_utils/src/toolbox_utils/readers/wdm.py
swmmtoolbox/toolbox_utils/tests/test_asbestfreq.py
swmmtoolbox/toolbox_utils/tests/test_date_slice.py
swmmtoolbox/toolbox_utils/tests/test_dateparse.py
swmmtoolbox/toolbox_utils/tests/test_extract.py
swmmtoolbox/toolbox_utils/tests/test_hbn.py
swmmtoolbox/toolbox_utils/tests/test_make_list.py
swmmtoolbox/toolbox_utils/tests/test_period_timestamp.py
swmmtoolbox/toolbox_utils/tests/test_plotgen.py
swmmtoolbox/toolbox_utils/tests/test_range_to_numlist.py
swmmtoolbox/toolbox_utils/tests/test_read.py
swmmtoolbox/toolbox_utils/tests/test_wdm.py
swmmtoolbox-4.0.15.dist-info/licenses/LICENSE.txt
swmmtoolbox-4.0.15.dist-info/METADATA
swmmtoolbox-4.0.15.dist-info/WHEEL
swmmtoolbox-4.0.15.dist-info/entry_points.txt
swmmtoolbox-4.0.15.dist-info/top_level.txt
swmmtoolbox-4.0.15.dist-info/RECORD
