Metadata-Version: 2.4
Name: swmmtoolbox
Version: 4.0.15
Summary: Command line script and Python library to read Storm Water Management Model binary output.
Author-email: Tim Cera <tim@cerazone.net>
License: BSD-3-Clause
Project-URL: documentation, https://timcera.bitbucket.io/swmmtoolbox/docs/index.html#swmmtoolbox-documentation
Project-URL: github, https://github.com/timcera/swmmtoolbox
Project-URL: bitbucket, https://bitbucket.org/timcera/swmmtoolbox/src/main/
Keywords: time-series,cli-app,swmm,stormwater,hydrograph,model,simulation,hydrology
Classifier: Development Status :: 5 - Production/Stable
Classifier: Intended Audience :: Science/Research
Classifier: Intended Audience :: End Users/Desktop
Classifier: Intended Audience :: Developers
Classifier: Environment :: Console
Classifier: License :: OSI Approved :: BSD License
Classifier: Natural Language :: English
Classifier: Operating System :: OS Independent
Classifier: Programming Language :: Python :: 3 :: Only
Classifier: Programming Language :: Python :: 3.8
Classifier: Programming Language :: Python :: 3.9
Classifier: Programming Language :: Python :: 3.10
Classifier: Programming Language :: Python :: 3.11
Classifier: Topic :: Scientific/Engineering :: Information Analysis
Classifier: Topic :: Scientific/Engineering
Classifier: Topic :: Software Development :: Libraries :: Python Modules
Requires-Python: >=3.8
License-File: LICENSE.txt
Requires-Dist: cltoolbox>=1.0.0
Requires-Dist: dateparser
Requires-Dist: numpy
Requires-Dist: pandas[excel]
Requires-Dist: pint!=0.21.*
Requires-Dist: pint<0.22; python_version < "3.9"
Requires-Dist: pint-pandas
Requires-Dist: pydantic
Requires-Dist: scipy
Requires-Dist: tabulate
Dynamic: license-file
